MANIFEST.in
README.md
setup.cfg
setup.py
tornform.py
tornform.egg-info/PKG-INFO
tornform.egg-info/SOURCES.txt
tornform.egg-info/dependency_links.txt
tornform.egg-info/requires.txt
tornform.egg-info/top_level.txt