Metadata-Version: 1.1
Name: tornform
Version: 0.1
Summary: # tornform is a form-wrapper with voluptuous for tornado
Home-page: http://github.com/likang/tornform
Author: Kang Li
Author-email: i@likang.me
License: MIT
Download-URL: http://pypi.python.org/pypi/tornform
Platform: any
